{
  "id": "MMR003003701",
  "level": 3,
  "level_name": {
    "local": "မြို့နယ်",
    "en": "Township"
  },
  "name": {
    "local": "ဖာပွန်",
    "en": "Hpapun",
    "slug": "hpapun-MMR003003701"
  },
  "code": {
    "id": "MMR003003701",
    "iso": null
  },
  "parent": {
    "id": "MMR003D004",
    "level": 2,
    "name": {
      "local": "ဖာပွန်ခရိုင်",
      "en": "Hpapun",
      "slug": "hpapun-MMR003D004"
    }
  },
  "ancestors": [
    {
      "id": "MMR003",
      "level": 1,
      "name": {
        "local": "ကရင်ပြည်နယ်",
        "en": "Kayin",
        "slug": "kayin-MMR003"
      }
    },
    {
      "id": "MMR003D004",
      "level": 2,
      "name": {
        "local": "ဖာပွန်ခရိုင်",
        "en": "Hpapun",
        "slug": "hpapun-MMR003D004"
      }
    }
  ],
  "children_count": {
    "ward": 37
  },
  "zip_codes": [],
  "geo": {
    "lat": "18.06306",
    "lon": "97.44321"
  },
  "metadata": {},
  "source": {}
}