[
  {
    "id": "0212217",
    "level": 4,
    "level_name": {
      "local": "ရပ်ကွက်/ကျေးရွာအုပ်စု",
      "en": "Ward/Village Tract"
    },
    "name": {
      "local": "အိုင်တောင် ကျေးရွာအုပ်စု",
      "en": "Aing Taung Village Tract",
      "slug": "aing-taung-village-tract-0212217"
    },
    "code": {
      "id": "0212217",
      "iso": null
    },
    "parent": {
      "id": "MMR005017701",
      "level": 3,
      "name": {
        "local": "ကနီ",
        "en": "Kani",
        "slug": "kani-MMR005017701"
      }
    },
    "ancestors": [
      {
        "id": "MMR005",
        "level": 1,
        "name": {
          "local": "စစ်ကိုင်းတိုင်းဒေသကြီး",
          "en": "Sagaing",
          "slug": "sagaing-MMR005"
        }
      },
      {
        "id": "MMR005D009",
        "level": 2,
        "name": {
          "local": "ယင်းမာပင်ခရိုင်",
          "en": "Yinmarbin",
          "slug": "yinmarbin-MMR005D009"
        }
      },
      {
        "id": "MMR005017701",
        "level": 3,
        "name": {
          "local": "ကနီ",
          "en": "Kani",
          "slug": "kani-MMR005017701"
        }
      }
    ],
    "children_count": {},
    "zip_codes": [
      "0212217"
    ],
    "geo": {
      "lat": null,
      "lon": null
    },
    "metadata": {},
    "source": {}
  },
  {
    "id": "0212240",
    "level": 4,
    "level_name": {
      "local": "ရပ်ကွက်/ကျေးရွာအုပ်စု",
      "en": "Ward/Village Tract"
    },
    "name": {
      "local": "ဘုတ်ကုန်း ကျေးရွာအုပ်စု",
      "en": "Boke Kone Village Tract",
      "slug": "boke-kone-village-tract-0212240"
    },
    "code": {
      "id": "0212240",
      "iso": null
    },
    "parent": {
      "id": "MMR005017701",
      "level": 3,
      "name": {
        "local": "ကနီ",
        "en": "Kani",
        "slug": "kani-MMR005017701"
      }
    },
    "ancestors": [
      {
        "id": "MMR005",
        "level": 1,
        "name": {
          "local": "စစ်ကိုင်းတိုင်းဒေသကြီး",
          "en": "Sagaing",
          "slug": "sagaing-MMR005"
        }
      },
      {
        "id": "MMR005D009",
        "level": 2,
        "name": {
          "local": "ယင်းမာပင်ခရိုင်",
          "en": "Yinmarbin",
          "slug": "yinmarbin-MMR005D009"
        }
      },
      {
        "id": "MMR005017701",
        "level": 3,
        "name": {
          "local": "ကနီ",
          "en": "Kani",
          "slug": "kani-MMR005017701"
        }
      }
    ],
    "children_count": {},
    "zip_codes": [
      "0212240"
    ],
    "geo": {
      "lat": null,
      "lon": null
    },
    "metadata": {},
    "source": {}
  },
  {
    "id": "0212224",
    "level": 4,
    "level_name": {
      "local": "ရပ်ကွက်/ကျေးရွာအုပ်စု",
      "en": "Ward/Village Tract"
    },
    "name": {
      "local": "ဘုမ္မဇင်း ကျေးရွာအုပ်စု",
      "en": "Bon Ma Zin Village Tract",
      "slug": "bon-ma-zin-village-tract-0212224"
    },
    "code": {
      "id": "0212224",
      "iso": null
    },
    "parent": {
      "id": "MMR005017701",
      "level": 3,
      "name": {
        "local": "ကနီ",
        "en": "Kani",
        "slug": "kani-MMR005017701"
      }
    },
    "ancestors": [
      {
        "id": "MMR005",
        "level": 1,
        "name": {
          "local": "စစ်ကိုင်းတိုင်းဒေသကြီး",
          "en": "Sagaing",
          "slug": "sagaing-MMR005"
        }
      },
      {
        "id": "MMR005D009",
        "level": 2,
        "name": {
          "local": "ယင်းမာပင်ခရိုင်",
          "en": "Yinmarbin",
          "slug": "yinmarbin-MMR005D009"
        }
      },
      {
        "id": "MMR005017701",
        "level": 3,
        "name": {
          "local": "ကနီ",
          "en": "Kani",
          "slug": "kani-MMR005017701"
        }
      }
    ],
    "children_count": {},
    "zip_codes": [
      "0212224"
    ],
    "geo": {
      "lat": null,
      "lon": null
    },
    "metadata": {},
    "source": {}
  },
  {
    "id": "0212215",
    "level": 4,
    "level_name": {
      "local": "ရပ်ကွက်/ကျေးရွာအုပ်စု",
      "en": "Ward/Village Tract"
    },
    "name": {
      "local": "ချိုင် ကျေးရွာအုပ်စု",
      "en": "Chaing Village Tract",
      "slug": "chaing-village-tract-0212215"
    },
    "code": {
      "id": "0212215",
      "iso": null
    },
    "parent": {
      "id": "MMR005017701",
      "level": 3,
      "name": {
        "local": "ကနီ",
        "en": "Kani",
        "slug": "kani-MMR005017701"
      }
    },
    "ancestors": [
      {
        "id": "MMR005",
        "level": 1,
        "name": {
          "local": "စစ်ကိုင်းတိုင်းဒေသကြီး",
          "en": "Sagaing",
          "slug": "sagaing-MMR005"
        }
      },
      {
        "id": "MMR005D009",
        "level": 2,
        "name": {
          "local": "ယင်းမာပင်ခရိုင်",
          "en": "Yinmarbin",
          "slug": "yinmarbin-MMR005D009"
        }
      },
      {
        "id": "MMR005017701",
        "level": 3,
        "name": {
          "local": "ကနီ",
          "en": "Kani",
          "slug": "kani-MMR005017701"
        }
      }
    ],
    "children_count": {},
    "zip_codes": [
      "0212215"
    ],
    "geo": {
      "lat": null,
      "lon": null
    },
    "metadata": {},
    "source": {}
  },
  {
    "id": "0212218",
    "level": 4,
    "level_name": {
      "local": "ရပ်ကွက်/ကျေးရွာအုပ်စု",
      "en": "Ward/Village Tract"
    },
    "name": {
      "local": "ချောင်းမ ကျေးရွာအုပ်စု",
      "en": "Chaung Ma Village Tract",
      "slug": "chaung-ma-village-tract-0212218"
    },
    "code": {
      "id": "0212218",
      "iso": null
    },
    "parent": {
      "id": "MMR005017701",
      "level": 3,
      "name": {
        "local": "ကနီ",
        "en": "Kani",
        "slug": "kani-MMR005017701"
      }
    },
    "ancestors": [
      {
        "id": "MMR005",
        "level": 1,
        "name": {
          "local": "စစ်ကိုင်းတိုင်းဒေသကြီး",
          "en": "Sagaing",
          "slug": "sagaing-MMR005"
        }
      },
      {
        "id": "MMR005D009",
        "level": 2,
        "name": {
          "local": "ယင်းမာပင်ခရိုင်",
          "en": "Yinmarbin",
          "slug": "yinmarbin-MMR005D009"
        }
      },
      {
        "id": "MMR005017701",
        "level": 3,
        "name": {
          "local": "ကနီ",
          "en": "Kani",
          "slug": "kani-MMR005017701"
        }
      }
    ],
    "children_count": {},
    "zip_codes": [
      "0212218"
    ],
    "geo": {
      "lat": null,
      "lon": null
    },
    "metadata": {},
    "source": {}
  },
  {
    "id": "0212228",
    "level": 4,
    "level_name": {
      "local": "ရပ်ကွက်/ကျေးရွာအုပ်စု",
      "en": "Ward/Village Tract"
    },
    "name": {
      "local": "ဒိုင်ကြီး ကျေးရွာအုပ်စု",
      "en": "Daing Gyi Village Tract",
      "slug": "daing-gyi-village-tract-0212228"
    },
    "code": {
      "id": "0212228",
      "iso": null
    },
    "parent": {
      "id": "MMR005017701",
      "level": 3,
      "name": {
        "local": "ကနီ",
        "en": "Kani",
        "slug": "kani-MMR005017701"
      }
    },
    "ancestors": [
      {
        "id": "MMR005",
        "level": 1,
        "name": {
          "local": "စစ်ကိုင်းတိုင်းဒေသကြီး",
          "en": "Sagaing",
          "slug": "sagaing-MMR005"
        }
      },
      {
        "id": "MMR005D009",
        "level": 2,
        "name": {
          "local": "ယင်းမာပင်ခရိုင်",
          "en": "Yinmarbin",
          "slug": "yinmarbin-MMR005D009"
        }
      },
      {
        "id": "MMR005017701",
        "level": 3,
        "name": {
          "local": "ကနီ",
          "en": "Kani",
          "slug": "kani-MMR005017701"
        }
      }
    ],
    "children_count": {},
    "zip_codes": [
      "0212228"
    ],
    "geo": {
      "lat": null,
      "lon": null
    },
    "metadata": {},
    "source": {}
  },
  {
    "id": "0212223",
    "level": 4,
    "level_name": {
      "local": "ရပ်ကွက်/ကျေးရွာအုပ်စု",
      "en": "Ward/Village Tract"
    },
    "name": {
      "local": "မျှိုင်း ကျေးရွာအုပ်စု",
      "en": "Hmyaing Village Tract",
      "slug": "hmyaing-village-tract-0212223"
    },
    "code": {
      "id": "0212223",
      "iso": null
    },
    "parent": {
      "id": "MMR005017701",
      "level": 3,
      "name": {
        "local": "ကနီ",
        "en": "Kani",
        "slug": "kani-MMR005017701"
      }
    },
    "ancestors": [
      {
        "id": "MMR005",
        "level": 1,
        "name": {
          "local": "စစ်ကိုင်းတိုင်းဒေသကြီး",
          "en": "Sagaing",
          "slug": "sagaing-MMR005"
        }
      },
      {
        "id": "MMR005D009",
        "level": 2,
        "name": {
          "local": "ယင်းမာပင်ခရိုင်",
          "en": "Yinmarbin",
          "slug": "yinmarbin-MMR005D009"
        }
      },
      {
        "id": "MMR005017701",
        "level": 3,
        "name": {
          "local": "ကနီ",
          "en": "Kani",
          "slug": "kani-MMR005017701"
        }
      }
    ],
    "children_count": {},
    "zip_codes": [
      "0212223"
    ],
    "geo": {
      "lat": null,
      "lon": null
    },
    "metadata": {},
    "source": {}
  },
  {
    "id": "0212237",
    "level": 4,
    "level_name": {
      "local": "ရပ်ကွက်/ကျေးရွာအုပ်စု",
      "en": "Ward/Village Tract"
    },
    "name": {
      "local": "ထနောင်းပကား ကျေးရွာအုပ်စု",
      "en": "Hta Naung Pa Kar Village Tract",
      "slug": "hta-naung-pa-kar-village-tract-0212237"
    },
    "code": {
      "id": "0212237",
      "iso": null
    },
    "parent": {
      "id": "MMR005017701",
      "level": 3,
      "name": {
        "local": "ကနီ",
        "en": "Kani",
        "slug": "kani-MMR005017701"
      }
    },
    "ancestors": [
      {
        "id": "MMR005",
        "level": 1,
        "name": {
          "local": "စစ်ကိုင်းတိုင်းဒေသကြီး",
          "en": "Sagaing",
          "slug": "sagaing-MMR005"
        }
      },
      {
        "id": "MMR005D009",
        "level": 2,
        "name": {
          "local": "ယင်းမာပင်ခရိုင်",
          "en": "Yinmarbin",
          "slug": "yinmarbin-MMR005D009"
        }
      },
      {
        "id": "MMR005017701",
        "level": 3,
        "name": {
          "local": "ကနီ",
          "en": "Kani",
          "slug": "kani-MMR005017701"
        }
      }
    ],
    "children_count": {},
    "zip_codes": [
      "0212237"
    ],
    "geo": {
      "lat": null,
      "lon": null
    },
    "metadata": {},
    "source": {}
  },
  {
    "id": "0212208",
    "level": 4,
    "level_name": {
      "local": "ရပ်ကွက်/ကျေးရွာအုပ်စု",
      "en": "Ward/Village Tract"
    },
    "name": {
      "local": "ထူးပေါက် ကျေးရွာအုပ်စု",
      "en": "Htu Pauk Village Tract",
      "slug": "htu-pauk-village-tract-0212208"
    },
    "code": {
      "id": "0212208",
      "iso": null
    },
    "parent": {
      "id": "MMR005017701",
      "level": 3,
      "name": {
        "local": "ကနီ",
        "en": "Kani",
        "slug": "kani-MMR005017701"
      }
    },
    "ancestors": [
      {
        "id": "MMR005",
        "level": 1,
        "name": {
          "local": "စစ်ကိုင်းတိုင်းဒေသကြီး",
          "en": "Sagaing",
          "slug": "sagaing-MMR005"
        }
      },
      {
        "id": "MMR005D009",
        "level": 2,
        "name": {
          "local": "ယင်းမာပင်ခရိုင်",
          "en": "Yinmarbin",
          "slug": "yinmarbin-MMR005D009"
        }
      },
      {
        "id": "MMR005017701",
        "level": 3,
        "name": {
          "local": "ကနီ",
          "en": "Kani",
          "slug": "kani-MMR005017701"
        }
      }
    ],
    "children_count": {},
    "zip_codes": [
      "0212208"
    ],
    "geo": {
      "lat": null,
      "lon": null
    },
    "metadata": {},
    "source": {}
  },
  {
    "id": "0212200",
    "level": 4,
    "level_name": {
      "local": "ရပ်ကွက်/ကျေးရွာအုပ်စု",
      "en": "Ward/Village Tract"
    },
    "name": {
      "local": "ကနဲ ကျေးရွာအုပ်စု",
      "en": "Ka Ne Village Tract",
      "slug": "ka-ne-village-tract-0212200"
    },
    "code": {
      "id": "0212200",
      "iso": null
    },
    "parent": {
      "id": "MMR005017701",
      "level": 3,
      "name": {
        "local": "ကနီ",
        "en": "Kani",
        "slug": "kani-MMR005017701"
      }
    },
    "ancestors": [
      {
        "id": "MMR005",
        "level": 1,
        "name": {
          "local": "စစ်ကိုင်းတိုင်းဒေသကြီး",
          "en": "Sagaing",
          "slug": "sagaing-MMR005"
        }
      },
      {
        "id": "MMR005D009",
        "level": 2,
        "name": {
          "local": "ယင်းမာပင်ခရိုင်",
          "en": "Yinmarbin",
          "slug": "yinmarbin-MMR005D009"
        }
      },
      {
        "id": "MMR005017701",
        "level": 3,
        "name": {
          "local": "ကနီ",
          "en": "Kani",
          "slug": "kani-MMR005017701"
        }
      }
    ],
    "children_count": {},
    "zip_codes": [
      "0212200"
    ],
    "geo": {
      "lat": null,
      "lon": null
    },
    "metadata": {},
    "source": {}
  },
  {
    "id": "0212225",
    "level": 4,
    "level_name": {
      "local": "ရပ်ကွက်/ကျေးရွာအုပ်စု",
      "en": "Ward/Village Tract"
    },
    "name": {
      "local": "ကဲတောင် ကျေးရွာအုပ်စု",
      "en": "Ke Taung Village Tract",
      "slug": "ke-taung-village-tract-0212225"
    },
    "code": {
      "id": "0212225",
      "iso": null
    },
    "parent": {
      "id": "MMR005017701",
      "level": 3,
      "name": {
        "local": "ကနီ",
        "en": "Kani",
        "slug": "kani-MMR005017701"
      }
    },
    "ancestors": [
      {
        "id": "MMR005",
        "level": 1,
        "name": {
          "local": "စစ်ကိုင်းတိုင်းဒေသကြီး",
          "en": "Sagaing",
          "slug": "sagaing-MMR005"
        }
      },
      {
        "id": "MMR005D009",
        "level": 2,
        "name": {
          "local": "ယင်းမာပင်ခရိုင်",
          "en": "Yinmarbin",
          "slug": "yinmarbin-MMR005D009"
        }
      },
      {
        "id": "MMR005017701",
        "level": 3,
        "name": {
          "local": "ကနီ",
          "en": "Kani",
          "slug": "kani-MMR005017701"
        }
      }
    ],
    "children_count": {},
    "zip_codes": [
      "0212225"
    ],
    "geo": {
      "lat": null,
      "lon": null
    },
    "metadata": {},
    "source": {}
  },
  {
    "id": "0212226",
    "level": 4,
    "level_name": {
      "local": "ရပ်ကွက်/ကျေးရွာအုပ်စု",
      "en": "Ward/Village Tract"
    },
    "name": {
      "local": "ခုံကြီး ကျေးရွာအုပ်စု",
      "en": "Khon Gyi Village Tract",
      "slug": "khon-gyi-village-tract-0212226"
    },
    "code": {
      "id": "0212226",
      "iso": null
    },
    "parent": {
      "id": "MMR005017701",
      "level": 3,
      "name": {
        "local": "ကနီ",
        "en": "Kani",
        "slug": "kani-MMR005017701"
      }
    },
    "ancestors": [
      {
        "id": "MMR005",
        "level": 1,
        "name": {
          "local": "စစ်ကိုင်းတိုင်းဒေသကြီး",
          "en": "Sagaing",
          "slug": "sagaing-MMR005"
        }
      },
      {
        "id": "MMR005D009",
        "level": 2,
        "name": {
          "local": "ယင်းမာပင်ခရိုင်",
          "en": "Yinmarbin",
          "slug": "yinmarbin-MMR005D009"
        }
      },
      {
        "id": "MMR005017701",
        "level": 3,
        "name": {
          "local": "ကနီ",
          "en": "Kani",
          "slug": "kani-MMR005017701"
        }
      }
    ],
    "children_count": {},
    "zip_codes": [
      "0212226"
    ],
    "geo": {
      "lat": null,
      "lon": null
    },
    "metadata": {},
    "source": {}
  },
  {
    "id": "0212211",
    "level": 4,
    "level_name": {
      "local": "ရပ်ကွက်/ကျေးရွာအုပ်စု",
      "en": "Ward/Village Tract"
    },
    "name": {
      "local": "ကင်းတောင် ကျေးရွာအုပ်စု",
      "en": "Kin Taung Village Tract",
      "slug": "kin-taung-village-tract-0212211"
    },
    "code": {
      "id": "0212211",
      "iso": null
    },
    "parent": {
      "id": "MMR005017701",
      "level": 3,
      "name": {
        "local": "ကနီ",
        "en": "Kani",
        "slug": "kani-MMR005017701"
      }
    },
    "ancestors": [
      {
        "id": "MMR005",
        "level": 1,
        "name": {
          "local": "စစ်ကိုင်းတိုင်းဒေသကြီး",
          "en": "Sagaing",
          "slug": "sagaing-MMR005"
        }
      },
      {
        "id": "MMR005D009",
        "level": 2,
        "name": {
          "local": "ယင်းမာပင်ခရိုင်",
          "en": "Yinmarbin",
          "slug": "yinmarbin-MMR005D009"
        }
      },
      {
        "id": "MMR005017701",
        "level": 3,
        "name": {
          "local": "ကနီ",
          "en": "Kani",
          "slug": "kani-MMR005017701"
        }
      }
    ],
    "children_count": {},
    "zip_codes": [
      "0212211"
    ],
    "geo": {
      "lat": null,
      "lon": null
    },
    "metadata": {},
    "source": {}
  },
  {
    "id": "0212243",
    "level": 4,
    "level_name": {
      "local": "ရပ်ကွက်/ကျေးရွာအုပ်စု",
      "en": "Ward/Village Tract"
    },
    "name": {
      "local": "ကင်း ကျေးရွာအုပ်စု",
      "en": "Kin Village Tract",
      "slug": "kin-village-tract-0212243"
    },
    "code": {
      "id": "0212243",
      "iso": null
    },
    "parent": {
      "id": "MMR005017701",
      "level": 3,
      "name": {
        "local": "ကနီ",
        "en": "Kani",
        "slug": "kani-MMR005017701"
      }
    },
    "ancestors": [
      {
        "id": "MMR005",
        "level": 1,
        "name": {
          "local": "စစ်ကိုင်းတိုင်းဒေသကြီး",
          "en": "Sagaing",
          "slug": "sagaing-MMR005"
        }
      },
      {
        "id": "MMR005D009",
        "level": 2,
        "name": {
          "local": "ယင်းမာပင်ခရိုင်",
          "en": "Yinmarbin",
          "slug": "yinmarbin-MMR005D009"
        }
      },
      {
        "id": "MMR005017701",
        "level": 3,
        "name": {
          "local": "ကနီ",
          "en": "Kani",
          "slug": "kani-MMR005017701"
        }
      }
    ],
    "children_count": {},
    "zip_codes": [
      "0212243"
    ],
    "geo": {
      "lat": null,
      "lon": null
    },
    "metadata": {},
    "source": {}
  },
  {
    "id": "0212244",
    "level": 4,
    "level_name": {
      "local": "ရပ်ကွက်/ကျေးရွာအုပ်စု",
      "en": "Ward/Village Tract"
    },
    "name": {
      "local": "ကူးဆိပ် ကျေးရွာအုပ်စု",
      "en": "Ku Seik Village Tract",
      "slug": "ku-seik-village-tract-0212244"
    },
    "code": {
      "id": "0212244",
      "iso": null
    },
    "parent": {
      "id": "MMR005017701",
      "level": 3,
      "name": {
        "local": "ကနီ",
        "en": "Kani",
        "slug": "kani-MMR005017701"
      }
    },
    "ancestors": [
      {
        "id": "MMR005",
        "level": 1,
        "name": {
          "local": "စစ်ကိုင်းတိုင်းဒေသကြီး",
          "en": "Sagaing",
          "slug": "sagaing-MMR005"
        }
      },
      {
        "id": "MMR005D009",
        "level": 2,
        "name": {
          "local": "ယင်းမာပင်ခရိုင်",
          "en": "Yinmarbin",
          "slug": "yinmarbin-MMR005D009"
        }
      },
      {
        "id": "MMR005017701",
        "level": 3,
        "name": {
          "local": "ကနီ",
          "en": "Kani",
          "slug": "kani-MMR005017701"
        }
      }
    ],
    "children_count": {},
    "zip_codes": [
      "0212244"
    ],
    "geo": {
      "lat": null,
      "lon": null
    },
    "metadata": {},
    "source": {}
  },
  {
    "id": "0212239",
    "level": 4,
    "level_name": {
      "local": "ရပ်ကွက်/ကျေးရွာအုပ်စု",
      "en": "Ward/Village Tract"
    },
    "name": {
      "local": "ကျော်ရွာ ကျေးရွာအုပ်စု",
      "en": "Kyaw Ywar Village Tract",
      "slug": "kyaw-ywar-village-tract-0212239"
    },
    "code": {
      "id": "0212239",
      "iso": null
    },
    "parent": {
      "id": "MMR005017701",
      "level": 3,
      "name": {
        "local": "ကနီ",
        "en": "Kani",
        "slug": "kani-MMR005017701"
      }
    },
    "ancestors": [
      {
        "id": "MMR005",
        "level": 1,
        "name": {
          "local": "စစ်ကိုင်းတိုင်းဒေသကြီး",
          "en": "Sagaing",
          "slug": "sagaing-MMR005"
        }
      },
      {
        "id": "MMR005D009",
        "level": 2,
        "name": {
          "local": "ယင်းမာပင်ခရိုင်",
          "en": "Yinmarbin",
          "slug": "yinmarbin-MMR005D009"
        }
      },
      {
        "id": "MMR005017701",
        "level": 3,
        "name": {
          "local": "ကနီ",
          "en": "Kani",
          "slug": "kani-MMR005017701"
        }
      }
    ],
    "children_count": {},
    "zip_codes": [
      "0212239"
    ],
    "geo": {
      "lat": null,
      "lon": null
    },
    "metadata": {},
    "source": {}
  },
  {
    "id": "0212210",
    "level": 4,
    "level_name": {
      "local": "ရပ်ကွက်/ကျေးရွာအုပ်စု",
      "en": "Ward/Village Tract"
    },
    "name": {
      "local": "ကျွန်းပင်အိုင် ကျေးရွာအုပ်စု",
      "en": "Kyun Pin Aing Village Tract",
      "slug": "kyun-pin-aing-village-tract-0212210"
    },
    "code": {
      "id": "0212210",
      "iso": null
    },
    "parent": {
      "id": "MMR005017701",
      "level": 3,
      "name": {
        "local": "ကနီ",
        "en": "Kani",
        "slug": "kani-MMR005017701"
      }
    },
    "ancestors": [
      {
        "id": "MMR005",
        "level": 1,
        "name": {
          "local": "စစ်ကိုင်းတိုင်းဒေသကြီး",
          "en": "Sagaing",
          "slug": "sagaing-MMR005"
        }
      },
      {
        "id": "MMR005D009",
        "level": 2,
        "name": {
          "local": "ယင်းမာပင်ခရိုင်",
          "en": "Yinmarbin",
          "slug": "yinmarbin-MMR005D009"
        }
      },
      {
        "id": "MMR005017701",
        "level": 3,
        "name": {
          "local": "ကနီ",
          "en": "Kani",
          "slug": "kani-MMR005017701"
        }
      }
    ],
    "children_count": {},
    "zip_codes": [
      "0212210"
    ],
    "geo": {
      "lat": null,
      "lon": null
    },
    "metadata": {},
    "source": {}
  },
  {
    "id": "0212227",
    "level": 4,
    "level_name": {
      "local": "ရပ်ကွက်/ကျေးရွာအုပ်စု",
      "en": "Ward/Village Tract"
    },
    "name": {
      "local": "လာပို့ ကျေးရွာအုပ်စု",
      "en": "Lar Poet Village Tract",
      "slug": "lar-poet-village-tract-0212227"
    },
    "code": {
      "id": "0212227",
      "iso": null
    },
    "parent": {
      "id": "MMR005017701",
      "level": 3,
      "name": {
        "local": "ကနီ",
        "en": "Kani",
        "slug": "kani-MMR005017701"
      }
    },
    "ancestors": [
      {
        "id": "MMR005",
        "level": 1,
        "name": {
          "local": "စစ်ကိုင်းတိုင်းဒေသကြီး",
          "en": "Sagaing",
          "slug": "sagaing-MMR005"
        }
      },
      {
        "id": "MMR005D009",
        "level": 2,
        "name": {
          "local": "ယင်းမာပင်ခရိုင်",
          "en": "Yinmarbin",
          "slug": "yinmarbin-MMR005D009"
        }
      },
      {
        "id": "MMR005017701",
        "level": 3,
        "name": {
          "local": "ကနီ",
          "en": "Kani",
          "slug": "kani-MMR005017701"
        }
      }
    ],
    "children_count": {},
    "zip_codes": [
      "0212227"
    ],
    "geo": {
      "lat": null,
      "lon": null
    },
    "metadata": {},
    "source": {}
  },
  {
    "id": "0212233",
    "level": 4,
    "level_name": {
      "local": "ရပ်ကွက်/ကျေးရွာအုပ်စု",
      "en": "Ward/Village Tract"
    },
    "name": {
      "local": "လယ်ရှည် ကျေးရွာအုပ်စု",
      "en": "Lel Shey Village Tract",
      "slug": "lel-shey-village-tract-0212233"
    },
    "code": {
      "id": "0212233",
      "iso": null
    },
    "parent": {
      "id": "MMR005017701",
      "level": 3,
      "name": {
        "local": "ကနီ",
        "en": "Kani",
        "slug": "kani-MMR005017701"
      }
    },
    "ancestors": [
      {
        "id": "MMR005",
        "level": 1,
        "name": {
          "local": "စစ်ကိုင်းတိုင်းဒေသကြီး",
          "en": "Sagaing",
          "slug": "sagaing-MMR005"
        }
      },
      {
        "id": "MMR005D009",
        "level": 2,
        "name": {
          "local": "ယင်းမာပင်ခရိုင်",
          "en": "Yinmarbin",
          "slug": "yinmarbin-MMR005D009"
        }
      },
      {
        "id": "MMR005017701",
        "level": 3,
        "name": {
          "local": "ကနီ",
          "en": "Kani",
          "slug": "kani-MMR005017701"
        }
      }
    ],
    "children_count": {},
    "zip_codes": [
      "0212233"
    ],
    "geo": {
      "lat": null,
      "lon": null
    },
    "metadata": {},
    "source": {}
  },
  {
    "id": "0212219",
    "level": 4,
    "level_name": {
      "local": "ရပ်ကွက်/ကျေးရွာအုပ်စု",
      "en": "Ward/Village Tract"
    },
    "name": {
      "local": "လင်ပုန်းရည် ကျေးရွာအုပ်စု",
      "en": "Lin Pone Yae Village Tract",
      "slug": "lin-pone-yae-village-tract-0212219"
    },
    "code": {
      "id": "0212219",
      "iso": null
    },
    "parent": {
      "id": "MMR005017701",
      "level": 3,
      "name": {
        "local": "ကနီ",
        "en": "Kani",
        "slug": "kani-MMR005017701"
      }
    },
    "ancestors": [
      {
        "id": "MMR005",
        "level": 1,
        "name": {
          "local": "စစ်ကိုင်းတိုင်းဒေသကြီး",
          "en": "Sagaing",
          "slug": "sagaing-MMR005"
        }
      },
      {
        "id": "MMR005D009",
        "level": 2,
        "name": {
          "local": "ယင်းမာပင်ခရိုင်",
          "en": "Yinmarbin",
          "slug": "yinmarbin-MMR005D009"
        }
      },
      {
        "id": "MMR005017701",
        "level": 3,
        "name": {
          "local": "ကနီ",
          "en": "Kani",
          "slug": "kani-MMR005017701"
        }
      }
    ],
    "children_count": {},
    "zip_codes": [
      "0212219"
    ],
    "geo": {
      "lat": null,
      "lon": null
    },
    "metadata": {},
    "source": {}
  },
  {
    "id": "0212235",
    "level": 4,
    "level_name": {
      "local": "ရပ်ကွက်/ကျေးရွာအုပ်စု",
      "en": "Ward/Village Tract"
    },
    "name": {
      "local": "မဲဒင် ကျေးရွာအုပ်စု",
      "en": "Me Din Village Tract",
      "slug": "me-din-village-tract-0212235"
    },
    "code": {
      "id": "0212235",
      "iso": null
    },
    "parent": {
      "id": "MMR005017701",
      "level": 3,
      "name": {
        "local": "ကနီ",
        "en": "Kani",
        "slug": "kani-MMR005017701"
      }
    },
    "ancestors": [
      {
        "id": "MMR005",
        "level": 1,
        "name": {
          "local": "စစ်ကိုင်းတိုင်းဒေသကြီး",
          "en": "Sagaing",
          "slug": "sagaing-MMR005"
        }
      },
      {
        "id": "MMR005D009",
        "level": 2,
        "name": {
          "local": "ယင်းမာပင်ခရိုင်",
          "en": "Yinmarbin",
          "slug": "yinmarbin-MMR005D009"
        }
      },
      {
        "id": "MMR005017701",
        "level": 3,
        "name": {
          "local": "ကနီ",
          "en": "Kani",
          "slug": "kani-MMR005017701"
        }
      }
    ],
    "children_count": {},
    "zip_codes": [
      "0212235"
    ],
    "geo": {
      "lat": null,
      "lon": null
    },
    "metadata": {},
    "source": {}
  },
  {
    "id": "0212205",
    "level": 4,
    "level_name": {
      "local": "ရပ်ကွက်/ကျေးရွာအုပ်စု",
      "en": "Ward/Village Tract"
    },
    "name": {
      "local": "မိုးကောင်း ကျေးရွာအုပ်စု",
      "en": "Moe Kaung Village Tract",
      "slug": "moe-kaung-village-tract-0212205"
    },
    "code": {
      "id": "0212205",
      "iso": null
    },
    "parent": {
      "id": "MMR005017701",
      "level": 3,
      "name": {
        "local": "ကနီ",
        "en": "Kani",
        "slug": "kani-MMR005017701"
      }
    },
    "ancestors": [
      {
        "id": "MMR005",
        "level": 1,
        "name": {
          "local": "စစ်ကိုင်းတိုင်းဒေသကြီး",
          "en": "Sagaing",
          "slug": "sagaing-MMR005"
        }
      },
      {
        "id": "MMR005D009",
        "level": 2,
        "name": {
          "local": "ယင်းမာပင်ခရိုင်",
          "en": "Yinmarbin",
          "slug": "yinmarbin-MMR005D009"
        }
      },
      {
        "id": "MMR005017701",
        "level": 3,
        "name": {
          "local": "ကနီ",
          "en": "Kani",
          "slug": "kani-MMR005017701"
        }
      }
    ],
    "children_count": {},
    "zip_codes": [
      "0212205"
    ],
    "geo": {
      "lat": null,
      "lon": null
    },
    "metadata": {},
    "source": {}
  },
  {
    "id": "0212216",
    "level": 4,
    "level_name": {
      "local": "ရပ်ကွက်/ကျေးရွာအုပ်စု",
      "en": "Ward/Village Tract"
    },
    "name": {
      "local": "မုဌော ကျေးရွာအုပ်စု",
      "en": "Mu Htaw Village Tract",
      "slug": "mu-htaw-village-tract-0212216"
    },
    "code": {
      "id": "0212216",
      "iso": null
    },
    "parent": {
      "id": "MMR005017701",
      "level": 3,
      "name": {
        "local": "ကနီ",
        "en": "Kani",
        "slug": "kani-MMR005017701"
      }
    },
    "ancestors": [
      {
        "id": "MMR005",
        "level": 1,
        "name": {
          "local": "စစ်ကိုင်းတိုင်းဒေသကြီး",
          "en": "Sagaing",
          "slug": "sagaing-MMR005"
        }
      },
      {
        "id": "MMR005D009",
        "level": 2,
        "name": {
          "local": "ယင်းမာပင်ခရိုင်",
          "en": "Yinmarbin",
          "slug": "yinmarbin-MMR005D009"
        }
      },
      {
        "id": "MMR005017701",
        "level": 3,
        "name": {
          "local": "ကနီ",
          "en": "Kani",
          "slug": "kani-MMR005017701"
        }
      }
    ],
    "children_count": {},
    "zip_codes": [
      "0212216"
    ],
    "geo": {
      "lat": null,
      "lon": null
    },
    "metadata": {},
    "source": {}
  },
  {
    "id": "0212203",
    "level": 4,
    "level_name": {
      "local": "ရပ်ကွက်/ကျေးရွာအုပ်စု",
      "en": "Ward/Village Tract"
    },
    "name": {
      "local": "နတ်ကြီး ကျေးရွာအုပ်စု",
      "en": "Nat Gyi Village Tract",
      "slug": "nat-gyi-village-tract-0212203"
    },
    "code": {
      "id": "0212203",
      "iso": null
    },
    "parent": {
      "id": "MMR005017701",
      "level": 3,
      "name": {
        "local": "ကနီ",
        "en": "Kani",
        "slug": "kani-MMR005017701"
      }
    },
    "ancestors": [
      {
        "id": "MMR005",
        "level": 1,
        "name": {
          "local": "စစ်ကိုင်းတိုင်းဒေသကြီး",
          "en": "Sagaing",
          "slug": "sagaing-MMR005"
        }
      },
      {
        "id": "MMR005D009",
        "level": 2,
        "name": {
          "local": "ယင်းမာပင်ခရိုင်",
          "en": "Yinmarbin",
          "slug": "yinmarbin-MMR005D009"
        }
      },
      {
        "id": "MMR005017701",
        "level": 3,
        "name": {
          "local": "ကနီ",
          "en": "Kani",
          "slug": "kani-MMR005017701"
        }
      }
    ],
    "children_count": {},
    "zip_codes": [
      "0212203"
    ],
    "geo": {
      "lat": null,
      "lon": null
    },
    "metadata": {},
    "source": {}
  },
  {
    "id": "0212231",
    "level": 4,
    "level_name": {
      "local": "ရပ်ကွက်/ကျေးရွာအုပ်စု",
      "en": "Ward/Village Tract"
    },
    "name": {
      "local": "နတ်လာပို့မြောက် ကျေးရွာအုပ်စု",
      "en": "Nat Lar Poet Myauk Village Tract",
      "slug": "nat-lar-poet-myauk-village-tract-0212231"
    },
    "code": {
      "id": "0212231",
      "iso": null
    },
    "parent": {
      "id": "MMR005017701",
      "level": 3,
      "name": {
        "local": "ကနီ",
        "en": "Kani",
        "slug": "kani-MMR005017701"
      }
    },
    "ancestors": [
      {
        "id": "MMR005",
        "level": 1,
        "name": {
          "local": "စစ်ကိုင်းတိုင်းဒေသကြီး",
          "en": "Sagaing",
          "slug": "sagaing-MMR005"
        }
      },
      {
        "id": "MMR005D009",
        "level": 2,
        "name": {
          "local": "ယင်းမာပင်ခရိုင်",
          "en": "Yinmarbin",
          "slug": "yinmarbin-MMR005D009"
        }
      },
      {
        "id": "MMR005017701",
        "level": 3,
        "name": {
          "local": "ကနီ",
          "en": "Kani",
          "slug": "kani-MMR005017701"
        }
      }
    ],
    "children_count": {},
    "zip_codes": [
      "0212231"
    ],
    "geo": {
      "lat": null,
      "lon": null
    },
    "metadata": {},
    "source": {}
  },
  {
    "id": "0212232",
    "level": 4,
    "level_name": {
      "local": "ရပ်ကွက်/ကျေးရွာအုပ်စု",
      "en": "Ward/Village Tract"
    },
    "name": {
      "local": "နတ်လာပို့တောင် ကျေးရွာအုပ်စု",
      "en": "Nat Lar Poet Taung Village Tract",
      "slug": "nat-lar-poet-taung-village-tract-0212232"
    },
    "code": {
      "id": "0212232",
      "iso": null
    },
    "parent": {
      "id": "MMR005017701",
      "level": 3,
      "name": {
        "local": "ကနီ",
        "en": "Kani",
        "slug": "kani-MMR005017701"
      }
    },
    "ancestors": [
      {
        "id": "MMR005",
        "level": 1,
        "name": {
          "local": "စစ်ကိုင်းတိုင်းဒေသကြီး",
          "en": "Sagaing",
          "slug": "sagaing-MMR005"
        }
      },
      {
        "id": "MMR005D009",
        "level": 2,
        "name": {
          "local": "ယင်းမာပင်ခရိုင်",
          "en": "Yinmarbin",
          "slug": "yinmarbin-MMR005D009"
        }
      },
      {
        "id": "MMR005017701",
        "level": 3,
        "name": {
          "local": "ကနီ",
          "en": "Kani",
          "slug": "kani-MMR005017701"
        }
      }
    ],
    "children_count": {},
    "zip_codes": [
      "0212232"
    ],
    "geo": {
      "lat": null,
      "lon": null
    },
    "metadata": {},
    "source": {}
  },
  {
    "id": "0212238",
    "level": 4,
    "level_name": {
      "local": "ရပ်ကွက်/ကျေးရွာအုပ်စု",
      "en": "Ward/Village Tract"
    },
    "name": {
      "local": "နတ်ရဲတောင် ကျေးရွာအုပ်စု",
      "en": "Nat Ye Taung Village Tract",
      "slug": "nat-ye-taung-village-tract-0212238"
    },
    "code": {
      "id": "0212238",
      "iso": null
    },
    "parent": {
      "id": "MMR005017701",
      "level": 3,
      "name": {
        "local": "ကနီ",
        "en": "Kani",
        "slug": "kani-MMR005017701"
      }
    },
    "ancestors": [
      {
        "id": "MMR005",
        "level": 1,
        "name": {
          "local": "စစ်ကိုင်းတိုင်းဒေသကြီး",
          "en": "Sagaing",
          "slug": "sagaing-MMR005"
        }
      },
      {
        "id": "MMR005D009",
        "level": 2,
        "name": {
          "local": "ယင်းမာပင်ခရိုင်",
          "en": "Yinmarbin",
          "slug": "yinmarbin-MMR005D009"
        }
      },
      {
        "id": "MMR005017701",
        "level": 3,
        "name": {
          "local": "ကနီ",
          "en": "Kani",
          "slug": "kani-MMR005017701"
        }
      }
    ],
    "children_count": {},
    "zip_codes": [
      "0212238"
    ],
    "geo": {
      "lat": null,
      "lon": null
    },
    "metadata": {},
    "source": {}
  },
  {
    "id": "0212001",
    "level": 4,
    "level_name": {
      "local": "ရပ်ကွက်/ကျေးရွာအုပ်စု",
      "en": "Ward/Village Tract"
    },
    "name": {
      "local": "အမှတ် (၁) ရပ်ကွက်",
      "en": "No (1) Quarter",
      "slug": "no-1-quarter-0212001"
    },
    "code": {
      "id": "0212001",
      "iso": null
    },
    "parent": {
      "id": "MMR005017701",
      "level": 3,
      "name": {
        "local": "ကနီ",
        "en": "Kani",
        "slug": "kani-MMR005017701"
      }
    },
    "ancestors": [
      {
        "id": "MMR005",
        "level": 1,
        "name": {
          "local": "စစ်ကိုင်းတိုင်းဒေသကြီး",
          "en": "Sagaing",
          "slug": "sagaing-MMR005"
        }
      },
      {
        "id": "MMR005D009",
        "level": 2,
        "name": {
          "local": "ယင်းမာပင်ခရိုင်",
          "en": "Yinmarbin",
          "slug": "yinmarbin-MMR005D009"
        }
      },
      {
        "id": "MMR005017701",
        "level": 3,
        "name": {
          "local": "ကနီ",
          "en": "Kani",
          "slug": "kani-MMR005017701"
        }
      }
    ],
    "children_count": {},
    "zip_codes": [
      "0212001"
    ],
    "geo": {
      "lat": null,
      "lon": null
    },
    "metadata": {},
    "source": {}
  },
  {
    "id": "0212002",
    "level": 4,
    "level_name": {
      "local": "ရပ်ကွက်/ကျေးရွာအုပ်စု",
      "en": "Ward/Village Tract"
    },
    "name": {
      "local": "အမှတ် (၂) ရပ်ကွက်",
      "en": "No (2) Quarter",
      "slug": "no-2-quarter-0212002"
    },
    "code": {
      "id": "0212002",
      "iso": null
    },
    "parent": {
      "id": "MMR005017701",
      "level": 3,
      "name": {
        "local": "ကနီ",
        "en": "Kani",
        "slug": "kani-MMR005017701"
      }
    },
    "ancestors": [
      {
        "id": "MMR005",
        "level": 1,
        "name": {
          "local": "စစ်ကိုင်းတိုင်းဒေသကြီး",
          "en": "Sagaing",
          "slug": "sagaing-MMR005"
        }
      },
      {
        "id": "MMR005D009",
        "level": 2,
        "name": {
          "local": "ယင်းမာပင်ခရိုင်",
          "en": "Yinmarbin",
          "slug": "yinmarbin-MMR005D009"
        }
      },
      {
        "id": "MMR005017701",
        "level": 3,
        "name": {
          "local": "ကနီ",
          "en": "Kani",
          "slug": "kani-MMR005017701"
        }
      }
    ],
    "children_count": {},
    "zip_codes": [
      "0212002"
    ],
    "geo": {
      "lat": null,
      "lon": null
    },
    "metadata": {},
    "source": {}
  },
  {
    "id": "0212003",
    "level": 4,
    "level_name": {
      "local": "ရပ်ကွက်/ကျေးရွာအုပ်စု",
      "en": "Ward/Village Tract"
    },
    "name": {
      "local": "အမှတ် (၃) ရပ်ကွက်",
      "en": "No (3) Quarter",
      "slug": "no-3-quarter-0212003"
    },
    "code": {
      "id": "0212003",
      "iso": null
    },
    "parent": {
      "id": "MMR005017701",
      "level": 3,
      "name": {
        "local": "ကနီ",
        "en": "Kani",
        "slug": "kani-MMR005017701"
      }
    },
    "ancestors": [
      {
        "id": "MMR005",
        "level": 1,
        "name": {
          "local": "စစ်ကိုင်းတိုင်းဒေသကြီး",
          "en": "Sagaing",
          "slug": "sagaing-MMR005"
        }
      },
      {
        "id": "MMR005D009",
        "level": 2,
        "name": {
          "local": "ယင်းမာပင်ခရိုင်",
          "en": "Yinmarbin",
          "slug": "yinmarbin-MMR005D009"
        }
      },
      {
        "id": "MMR005017701",
        "level": 3,
        "name": {
          "local": "ကနီ",
          "en": "Kani",
          "slug": "kani-MMR005017701"
        }
      }
    ],
    "children_count": {},
    "zip_codes": [
      "0212003"
    ],
    "geo": {
      "lat": null,
      "lon": null
    },
    "metadata": {},
    "source": {}
  },
  {
    "id": "0212230",
    "level": 4,
    "level_name": {
      "local": "ရပ်ကွက်/ကျေးရွာအုပ်စု",
      "en": "Ward/Village Tract"
    },
    "name": {
      "local": "တဇယ်ချောင် ကျေးရွာအုပ်စု",
      "en": "No (3) Ward Village Tract",
      "slug": "no-3-ward-village-tract-0212230"
    },
    "code": {
      "id": "0212230",
      "iso": null
    },
    "parent": {
      "id": "MMR005017701",
      "level": 3,
      "name": {
        "local": "ကနီ",
        "en": "Kani",
        "slug": "kani-MMR005017701"
      }
    },
    "ancestors": [
      {
        "id": "MMR005",
        "level": 1,
        "name": {
          "local": "စစ်ကိုင်းတိုင်းဒေသကြီး",
          "en": "Sagaing",
          "slug": "sagaing-MMR005"
        }
      },
      {
        "id": "MMR005D009",
        "level": 2,
        "name": {
          "local": "ယင်းမာပင်ခရိုင်",
          "en": "Yinmarbin",
          "slug": "yinmarbin-MMR005D009"
        }
      },
      {
        "id": "MMR005017701",
        "level": 3,
        "name": {
          "local": "ကနီ",
          "en": "Kani",
          "slug": "kani-MMR005017701"
        }
      }
    ],
    "children_count": {},
    "zip_codes": [
      "0212230"
    ],
    "geo": {
      "lat": null,
      "lon": null
    },
    "metadata": {},
    "source": {}
  },
  {
    "id": "0212241",
    "level": 4,
    "level_name": {
      "local": "ရပ်ကွက်/ကျေးရွာအုပ်စု",
      "en": "Ward/Village Tract"
    },
    "name": {
      "local": "အုမ္မ ကျေးရွာအုပ်စု",
      "en": "Ohn Ma Village Tract",
      "slug": "ohn-ma-village-tract-0212241"
    },
    "code": {
      "id": "0212241",
      "iso": null
    },
    "parent": {
      "id": "MMR005017701",
      "level": 3,
      "name": {
        "local": "ကနီ",
        "en": "Kani",
        "slug": "kani-MMR005017701"
      }
    },
    "ancestors": [
      {
        "id": "MMR005",
        "level": 1,
        "name": {
          "local": "စစ်ကိုင်းတိုင်းဒေသကြီး",
          "en": "Sagaing",
          "slug": "sagaing-MMR005"
        }
      },
      {
        "id": "MMR005D009",
        "level": 2,
        "name": {
          "local": "ယင်းမာပင်ခရိုင်",
          "en": "Yinmarbin",
          "slug": "yinmarbin-MMR005D009"
        }
      },
      {
        "id": "MMR005017701",
        "level": 3,
        "name": {
          "local": "ကနီ",
          "en": "Kani",
          "slug": "kani-MMR005017701"
        }
      }
    ],
    "children_count": {},
    "zip_codes": [
      "0212241"
    ],
    "geo": {
      "lat": null,
      "lon": null
    },
    "metadata": {},
    "source": {}
  },
  {
    "id": "0212202",
    "level": 4,
    "level_name": {
      "local": "ရပ်ကွက်/ကျေးရွာအုပ်စု",
      "en": "Ward/Village Tract"
    },
    "name": {
      "local": "စကမြား ကျေးရွာအုပ်စု",
      "en": "Sa Ka Myar Village Tract",
      "slug": "sa-ka-myar-village-tract-0212202"
    },
    "code": {
      "id": "0212202",
      "iso": null
    },
    "parent": {
      "id": "MMR005017701",
      "level": 3,
      "name": {
        "local": "ကနီ",
        "en": "Kani",
        "slug": "kani-MMR005017701"
      }
    },
    "ancestors": [
      {
        "id": "MMR005",
        "level": 1,
        "name": {
          "local": "စစ်ကိုင်းတိုင်းဒေသကြီး",
          "en": "Sagaing",
          "slug": "sagaing-MMR005"
        }
      },
      {
        "id": "MMR005D009",
        "level": 2,
        "name": {
          "local": "ယင်းမာပင်ခရိုင်",
          "en": "Yinmarbin",
          "slug": "yinmarbin-MMR005D009"
        }
      },
      {
        "id": "MMR005017701",
        "level": 3,
        "name": {
          "local": "ကနီ",
          "en": "Kani",
          "slug": "kani-MMR005017701"
        }
      }
    ],
    "children_count": {},
    "zip_codes": [
      "0212202"
    ],
    "geo": {
      "lat": null,
      "lon": null
    },
    "metadata": {},
    "source": {}
  },
  {
    "id": "0212236",
    "level": 4,
    "level_name": {
      "local": "ရပ်ကွက်/ကျေးရွာအုပ်စု",
      "en": "Ward/Village Tract"
    },
    "name": {
      "local": "ဆင်အို ကျေးရွာအုပ်စု",
      "en": "Sin Oh Village Tract",
      "slug": "sin-oh-village-tract-0212236"
    },
    "code": {
      "id": "0212236",
      "iso": null
    },
    "parent": {
      "id": "MMR005017701",
      "level": 3,
      "name": {
        "local": "ကနီ",
        "en": "Kani",
        "slug": "kani-MMR005017701"
      }
    },
    "ancestors": [
      {
        "id": "MMR005",
        "level": 1,
        "name": {
          "local": "စစ်ကိုင်းတိုင်းဒေသကြီး",
          "en": "Sagaing",
          "slug": "sagaing-MMR005"
        }
      },
      {
        "id": "MMR005D009",
        "level": 2,
        "name": {
          "local": "ယင်းမာပင်ခရိုင်",
          "en": "Yinmarbin",
          "slug": "yinmarbin-MMR005D009"
        }
      },
      {
        "id": "MMR005017701",
        "level": 3,
        "name": {
          "local": "ကနီ",
          "en": "Kani",
          "slug": "kani-MMR005017701"
        }
      }
    ],
    "children_count": {},
    "zip_codes": [
      "0212236"
    ],
    "geo": {
      "lat": null,
      "lon": null
    },
    "metadata": {},
    "source": {}
  },
  {
    "id": "0212201",
    "level": 4,
    "level_name": {
      "local": "ရပ်ကွက်/ကျေးရွာအုပ်စု",
      "en": "Ward/Village Tract"
    },
    "name": {
      "local": "ဆူးလေကုန်း ကျေးရွာအုပ်စု",
      "en": "Su Lay Kone Village Tract",
      "slug": "su-lay-kone-village-tract-0212201"
    },
    "code": {
      "id": "0212201",
      "iso": null
    },
    "parent": {
      "id": "MMR005017701",
      "level": 3,
      "name": {
        "local": "ကနီ",
        "en": "Kani",
        "slug": "kani-MMR005017701"
      }
    },
    "ancestors": [
      {
        "id": "MMR005",
        "level": 1,
        "name": {
          "local": "စစ်ကိုင်းတိုင်းဒေသကြီး",
          "en": "Sagaing",
          "slug": "sagaing-MMR005"
        }
      },
      {
        "id": "MMR005D009",
        "level": 2,
        "name": {
          "local": "ယင်းမာပင်ခရိုင်",
          "en": "Yinmarbin",
          "slug": "yinmarbin-MMR005D009"
        }
      },
      {
        "id": "MMR005017701",
        "level": 3,
        "name": {
          "local": "ကနီ",
          "en": "Kani",
          "slug": "kani-MMR005017701"
        }
      }
    ],
    "children_count": {},
    "zip_codes": [
      "0212201"
    ],
    "geo": {
      "lat": null,
      "lon": null
    },
    "metadata": {},
    "source": {}
  },
  {
    "id": "0212206",
    "level": 4,
    "level_name": {
      "local": "ရပ်ကွက်/ကျေးရွာအုပ်စု",
      "en": "Ward/Village Tract"
    },
    "name": {
      "local": "တပေါင်း ကျေးရွာအုပ်စု",
      "en": "Ta Paung Village Tract",
      "slug": "ta-paung-village-tract-0212206"
    },
    "code": {
      "id": "0212206",
      "iso": null
    },
    "parent": {
      "id": "MMR005017701",
      "level": 3,
      "name": {
        "local": "ကနီ",
        "en": "Kani",
        "slug": "kani-MMR005017701"
      }
    },
    "ancestors": [
      {
        "id": "MMR005",
        "level": 1,
        "name": {
          "local": "စစ်ကိုင်းတိုင်းဒေသကြီး",
          "en": "Sagaing",
          "slug": "sagaing-MMR005"
        }
      },
      {
        "id": "MMR005D009",
        "level": 2,
        "name": {
          "local": "ယင်းမာပင်ခရိုင်",
          "en": "Yinmarbin",
          "slug": "yinmarbin-MMR005D009"
        }
      },
      {
        "id": "MMR005017701",
        "level": 3,
        "name": {
          "local": "ကနီ",
          "en": "Kani",
          "slug": "kani-MMR005017701"
        }
      }
    ],
    "children_count": {},
    "zip_codes": [
      "0212206"
    ],
    "geo": {
      "lat": null,
      "lon": null
    },
    "metadata": {},
    "source": {}
  },
  {
    "id": "0212207",
    "level": 4,
    "level_name": {
      "local": "ရပ်ကွက်/ကျေးရွာအုပ်စု",
      "en": "Ward/Village Tract"
    },
    "name": {
      "local": "တပုန်း ကျေးရွာအုပ်စု",
      "en": "Ta Pone Village Tract",
      "slug": "ta-pone-village-tract-0212207"
    },
    "code": {
      "id": "0212207",
      "iso": null
    },
    "parent": {
      "id": "MMR005017701",
      "level": 3,
      "name": {
        "local": "ကနီ",
        "en": "Kani",
        "slug": "kani-MMR005017701"
      }
    },
    "ancestors": [
      {
        "id": "MMR005",
        "level": 1,
        "name": {
          "local": "စစ်ကိုင်းတိုင်းဒေသကြီး",
          "en": "Sagaing",
          "slug": "sagaing-MMR005"
        }
      },
      {
        "id": "MMR005D009",
        "level": 2,
        "name": {
          "local": "ယင်းမာပင်ခရိုင်",
          "en": "Yinmarbin",
          "slug": "yinmarbin-MMR005D009"
        }
      },
      {
        "id": "MMR005017701",
        "level": 3,
        "name": {
          "local": "ကနီ",
          "en": "Kani",
          "slug": "kani-MMR005017701"
        }
      }
    ],
    "children_count": {},
    "zip_codes": [
      "0212207"
    ],
    "geo": {
      "lat": null,
      "lon": null
    },
    "metadata": {},
    "source": {}
  },
  {
    "id": "0212212",
    "level": 4,
    "level_name": {
      "local": "ရပ်ကွက်/ကျေးရွာအုပ်စု",
      "en": "Ward/Village Tract"
    },
    "name": {
      "local": "တောင်ပေါက် ကျေးရွာအုပ်စု",
      "en": "Taung Pauk Village Tract",
      "slug": "taung-pauk-village-tract-0212212"
    },
    "code": {
      "id": "0212212",
      "iso": null
    },
    "parent": {
      "id": "MMR005017701",
      "level": 3,
      "name": {
        "local": "ကနီ",
        "en": "Kani",
        "slug": "kani-MMR005017701"
      }
    },
    "ancestors": [
      {
        "id": "MMR005",
        "level": 1,
        "name": {
          "local": "စစ်ကိုင်းတိုင်းဒေသကြီး",
          "en": "Sagaing",
          "slug": "sagaing-MMR005"
        }
      },
      {
        "id": "MMR005D009",
        "level": 2,
        "name": {
          "local": "ယင်းမာပင်ခရိုင်",
          "en": "Yinmarbin",
          "slug": "yinmarbin-MMR005D009"
        }
      },
      {
        "id": "MMR005017701",
        "level": 3,
        "name": {
          "local": "ကနီ",
          "en": "Kani",
          "slug": "kani-MMR005017701"
        }
      }
    ],
    "children_count": {},
    "zip_codes": [
      "0212212"
    ],
    "geo": {
      "lat": null,
      "lon": null
    },
    "metadata": {},
    "source": {}
  },
  {
    "id": "0212214",
    "level": 4,
    "level_name": {
      "local": "ရပ်ကွက်/ကျေးရွာအုပ်စု",
      "en": "Ward/Village Tract"
    },
    "name": {
      "local": "သမင်ခြံ ကျေးရွာအုပ်စု",
      "en": "Tha Min Chan Village Tract",
      "slug": "tha-min-chan-village-tract-0212214"
    },
    "code": {
      "id": "0212214",
      "iso": null
    },
    "parent": {
      "id": "MMR005017701",
      "level": 3,
      "name": {
        "local": "ကနီ",
        "en": "Kani",
        "slug": "kani-MMR005017701"
      }
    },
    "ancestors": [
      {
        "id": "MMR005",
        "level": 1,
        "name": {
          "local": "စစ်ကိုင်းတိုင်းဒေသကြီး",
          "en": "Sagaing",
          "slug": "sagaing-MMR005"
        }
      },
      {
        "id": "MMR005D009",
        "level": 2,
        "name": {
          "local": "ယင်းမာပင်ခရိုင်",
          "en": "Yinmarbin",
          "slug": "yinmarbin-MMR005D009"
        }
      },
      {
        "id": "MMR005017701",
        "level": 3,
        "name": {
          "local": "ကနီ",
          "en": "Kani",
          "slug": "kani-MMR005017701"
        }
      }
    ],
    "children_count": {},
    "zip_codes": [
      "0212214"
    ],
    "geo": {
      "lat": null,
      "lon": null
    },
    "metadata": {},
    "source": {}
  },
  {
    "id": "0212221",
    "level": 4,
    "level_name": {
      "local": "ရပ်ကွက်/ကျေးရွာအုပ်စု",
      "en": "Ward/Village Tract"
    },
    "name": {
      "local": "တွင်း ကျေးရွာအုပ်စု",
      "en": "Twin Village Tract",
      "slug": "twin-village-tract-0212221"
    },
    "code": {
      "id": "0212221",
      "iso": null
    },
    "parent": {
      "id": "MMR005017701",
      "level": 3,
      "name": {
        "local": "ကနီ",
        "en": "Kani",
        "slug": "kani-MMR005017701"
      }
    },
    "ancestors": [
      {
        "id": "MMR005",
        "level": 1,
        "name": {
          "local": "စစ်ကိုင်းတိုင်းဒေသကြီး",
          "en": "Sagaing",
          "slug": "sagaing-MMR005"
        }
      },
      {
        "id": "MMR005D009",
        "level": 2,
        "name": {
          "local": "ယင်းမာပင်ခရိုင်",
          "en": "Yinmarbin",
          "slug": "yinmarbin-MMR005D009"
        }
      },
      {
        "id": "MMR005017701",
        "level": 3,
        "name": {
          "local": "ကနီ",
          "en": "Kani",
          "slug": "kani-MMR005017701"
        }
      }
    ],
    "children_count": {},
    "zip_codes": [
      "0212221"
    ],
    "geo": {
      "lat": null,
      "lon": null
    },
    "metadata": {},
    "source": {}
  },
  {
    "id": "0212204",
    "level": 4,
    "level_name": {
      "local": "ရပ်ကွက်/ကျေးရွာအုပ်စု",
      "en": "Ward/Village Tract"
    },
    "name": {
      "local": "ဝယာ ကျေးရွာအုပ်စု",
      "en": "Wa Yar Village Tract",
      "slug": "wa-yar-village-tract-0212204"
    },
    "code": {
      "id": "0212204",
      "iso": null
    },
    "parent": {
      "id": "MMR005017701",
      "level": 3,
      "name": {
        "local": "ကနီ",
        "en": "Kani",
        "slug": "kani-MMR005017701"
      }
    },
    "ancestors": [
      {
        "id": "MMR005",
        "level": 1,
        "name": {
          "local": "စစ်ကိုင်းတိုင်းဒေသကြီး",
          "en": "Sagaing",
          "slug": "sagaing-MMR005"
        }
      },
      {
        "id": "MMR005D009",
        "level": 2,
        "name": {
          "local": "ယင်းမာပင်ခရိုင်",
          "en": "Yinmarbin",
          "slug": "yinmarbin-MMR005D009"
        }
      },
      {
        "id": "MMR005017701",
        "level": 3,
        "name": {
          "local": "ကနီ",
          "en": "Kani",
          "slug": "kani-MMR005017701"
        }
      }
    ],
    "children_count": {},
    "zip_codes": [
      "0212204"
    ],
    "geo": {
      "lat": null,
      "lon": null
    },
    "metadata": {},
    "source": {}
  },
  {
    "id": "0212209",
    "level": 4,
    "level_name": {
      "local": "ရပ်ကွက်/ကျေးရွာအုပ်စု",
      "en": "Ward/Village Tract"
    },
    "name": {
      "local": "ဝင်မနား ကျေးရွာအုပ်စု",
      "en": "Win Ma Nar Village Tract",
      "slug": "win-ma-nar-village-tract-0212209"
    },
    "code": {
      "id": "0212209",
      "iso": null
    },
    "parent": {
      "id": "MMR005017701",
      "level": 3,
      "name": {
        "local": "ကနီ",
        "en": "Kani",
        "slug": "kani-MMR005017701"
      }
    },
    "ancestors": [
      {
        "id": "MMR005",
        "level": 1,
        "name": {
          "local": "စစ်ကိုင်းတိုင်းဒေသကြီး",
          "en": "Sagaing",
          "slug": "sagaing-MMR005"
        }
      },
      {
        "id": "MMR005D009",
        "level": 2,
        "name": {
          "local": "ယင်းမာပင်ခရိုင်",
          "en": "Yinmarbin",
          "slug": "yinmarbin-MMR005D009"
        }
      },
      {
        "id": "MMR005017701",
        "level": 3,
        "name": {
          "local": "ကနီ",
          "en": "Kani",
          "slug": "kani-MMR005017701"
        }
      }
    ],
    "children_count": {},
    "zip_codes": [
      "0212209"
    ],
    "geo": {
      "lat": null,
      "lon": null
    },
    "metadata": {},
    "source": {}
  },
  {
    "id": "0212234",
    "level": 4,
    "level_name": {
      "local": "ရပ်ကွက်/ကျေးရွာအုပ်စု",
      "en": "Ward/Village Tract"
    },
    "name": {
      "local": "ယာကြီး ကျေးရွာအုပ်စု",
      "en": "Yar Gyi Village Tract",
      "slug": "yar-gyi-village-tract-0212234"
    },
    "code": {
      "id": "0212234",
      "iso": null
    },
    "parent": {
      "id": "MMR005017701",
      "level": 3,
      "name": {
        "local": "ကနီ",
        "en": "Kani",
        "slug": "kani-MMR005017701"
      }
    },
    "ancestors": [
      {
        "id": "MMR005",
        "level": 1,
        "name": {
          "local": "စစ်ကိုင်းတိုင်းဒေသကြီး",
          "en": "Sagaing",
          "slug": "sagaing-MMR005"
        }
      },
      {
        "id": "MMR005D009",
        "level": 2,
        "name": {
          "local": "ယင်းမာပင်ခရိုင်",
          "en": "Yinmarbin",
          "slug": "yinmarbin-MMR005D009"
        }
      },
      {
        "id": "MMR005017701",
        "level": 3,
        "name": {
          "local": "ကနီ",
          "en": "Kani",
          "slug": "kani-MMR005017701"
        }
      }
    ],
    "children_count": {},
    "zip_codes": [
      "0212234"
    ],
    "geo": {
      "lat": null,
      "lon": null
    },
    "metadata": {},
    "source": {}
  },
  {
    "id": "0212213",
    "level": 4,
    "level_name": {
      "local": "ရပ်ကွက်/ကျေးရွာအုပ်စု",
      "en": "Ward/Village Tract"
    },
    "name": {
      "local": "ယက္ကန်းတိုင် ကျေးရွာအုပ်စု",
      "en": "Yet Kan Taing Village Tract",
      "slug": "yet-kan-taing-village-tract-0212213"
    },
    "code": {
      "id": "0212213",
      "iso": null
    },
    "parent": {
      "id": "MMR005017701",
      "level": 3,
      "name": {
        "local": "ကနီ",
        "en": "Kani",
        "slug": "kani-MMR005017701"
      }
    },
    "ancestors": [
      {
        "id": "MMR005",
        "level": 1,
        "name": {
          "local": "စစ်ကိုင်းတိုင်းဒေသကြီး",
          "en": "Sagaing",
          "slug": "sagaing-MMR005"
        }
      },
      {
        "id": "MMR005D009",
        "level": 2,
        "name": {
          "local": "ယင်းမာပင်ခရိုင်",
          "en": "Yinmarbin",
          "slug": "yinmarbin-MMR005D009"
        }
      },
      {
        "id": "MMR005017701",
        "level": 3,
        "name": {
          "local": "ကနီ",
          "en": "Kani",
          "slug": "kani-MMR005017701"
        }
      }
    ],
    "children_count": {},
    "zip_codes": [
      "0212213"
    ],
    "geo": {
      "lat": null,
      "lon": null
    },
    "metadata": {},
    "source": {}
  },
  {
    "id": "0212229",
    "level": 4,
    "level_name": {
      "local": "ရပ်ကွက်/ကျေးရွာအုပ်စု",
      "en": "Ward/Village Tract"
    },
    "name": {
      "local": "ယင်းသွင် ကျေးရွာအုပ်စု",
      "en": "Yin Thwin Village Tract",
      "slug": "yin-thwin-village-tract-0212229"
    },
    "code": {
      "id": "0212229",
      "iso": null
    },
    "parent": {
      "id": "MMR005017701",
      "level": 3,
      "name": {
        "local": "ကနီ",
        "en": "Kani",
        "slug": "kani-MMR005017701"
      }
    },
    "ancestors": [
      {
        "id": "MMR005",
        "level": 1,
        "name": {
          "local": "စစ်ကိုင်းတိုင်းဒေသကြီး",
          "en": "Sagaing",
          "slug": "sagaing-MMR005"
        }
      },
      {
        "id": "MMR005D009",
        "level": 2,
        "name": {
          "local": "ယင်းမာပင်ခရိုင်",
          "en": "Yinmarbin",
          "slug": "yinmarbin-MMR005D009"
        }
      },
      {
        "id": "MMR005017701",
        "level": 3,
        "name": {
          "local": "ကနီ",
          "en": "Kani",
          "slug": "kani-MMR005017701"
        }
      }
    ],
    "children_count": {},
    "zip_codes": [
      "0212229"
    ],
    "geo": {
      "lat": null,
      "lon": null
    },
    "metadata": {},
    "source": {}
  },
  {
    "id": "0212242",
    "level": 4,
    "level_name": {
      "local": "ရပ်ကွက်/ကျေးရွာအုပ်စု",
      "en": "Ward/Village Tract"
    },
    "name": {
      "local": "ယင်း ကျေးရွာအုပ်စု",
      "en": "Yin Village Tract",
      "slug": "yin-village-tract-0212242"
    },
    "code": {
      "id": "0212242",
      "iso": null
    },
    "parent": {
      "id": "MMR005017701",
      "level": 3,
      "name": {
        "local": "ကနီ",
        "en": "Kani",
        "slug": "kani-MMR005017701"
      }
    },
    "ancestors": [
      {
        "id": "MMR005",
        "level": 1,
        "name": {
          "local": "စစ်ကိုင်းတိုင်းဒေသကြီး",
          "en": "Sagaing",
          "slug": "sagaing-MMR005"
        }
      },
      {
        "id": "MMR005D009",
        "level": 2,
        "name": {
          "local": "ယင်းမာပင်ခရိုင်",
          "en": "Yinmarbin",
          "slug": "yinmarbin-MMR005D009"
        }
      },
      {
        "id": "MMR005017701",
        "level": 3,
        "name": {
          "local": "ကနီ",
          "en": "Kani",
          "slug": "kani-MMR005017701"
        }
      }
    ],
    "children_count": {},
    "zip_codes": [
      "0212242"
    ],
    "geo": {
      "lat": null,
      "lon": null
    },
    "metadata": {},
    "source": {}
  },
  {
    "id": "0212222",
    "level": 4,
    "level_name": {
      "local": "ရပ်ကွက်/ကျေးရွာအုပ်စု",
      "en": "Ward/Village Tract"
    },
    "name": {
      "local": "ယင်းယိမ် ကျေးရွာအုပ်စု",
      "en": "Yin Yein Village Tract",
      "slug": "yin-yein-village-tract-0212222"
    },
    "code": {
      "id": "0212222",
      "iso": null
    },
    "parent": {
      "id": "MMR005017701",
      "level": 3,
      "name": {
        "local": "ကနီ",
        "en": "Kani",
        "slug": "kani-MMR005017701"
      }
    },
    "ancestors": [
      {
        "id": "MMR005",
        "level": 1,
        "name": {
          "local": "စစ်ကိုင်းတိုင်းဒေသကြီး",
          "en": "Sagaing",
          "slug": "sagaing-MMR005"
        }
      },
      {
        "id": "MMR005D009",
        "level": 2,
        "name": {
          "local": "ယင်းမာပင်ခရိုင်",
          "en": "Yinmarbin",
          "slug": "yinmarbin-MMR005D009"
        }
      },
      {
        "id": "MMR005017701",
        "level": 3,
        "name": {
          "local": "ကနီ",
          "en": "Kani",
          "slug": "kani-MMR005017701"
        }
      }
    ],
    "children_count": {},
    "zip_codes": [
      "0212222"
    ],
    "geo": {
      "lat": null,
      "lon": null
    },
    "metadata": {},
    "source": {}
  },
  {
    "id": "0212220",
    "level": 4,
    "level_name": {
      "local": "ရပ်ကွက်/ကျေးရွာအုပ်စု",
      "en": "Ward/Village Tract"
    },
    "name": {
      "local": "ဇီးပင်တွင်း ကျေးရွာအုပ်စု",
      "en": "Zee Pin Twin Village Tract",
      "slug": "zee-pin-twin-village-tract-0212220"
    },
    "code": {
      "id": "0212220",
      "iso": null
    },
    "parent": {
      "id": "MMR005017701",
      "level": 3,
      "name": {
        "local": "ကနီ",
        "en": "Kani",
        "slug": "kani-MMR005017701"
      }
    },
    "ancestors": [
      {
        "id": "MMR005",
        "level": 1,
        "name": {
          "local": "စစ်ကိုင်းတိုင်းဒေသကြီး",
          "en": "Sagaing",
          "slug": "sagaing-MMR005"
        }
      },
      {
        "id": "MMR005D009",
        "level": 2,
        "name": {
          "local": "ယင်းမာပင်ခရိုင်",
          "en": "Yinmarbin",
          "slug": "yinmarbin-MMR005D009"
        }
      },
      {
        "id": "MMR005017701",
        "level": 3,
        "name": {
          "local": "ကနီ",
          "en": "Kani",
          "slug": "kani-MMR005017701"
        }
      }
    ],
    "children_count": {},
    "zip_codes": [
      "0212220"
    ],
    "geo": {
      "lat": null,
      "lon": null
    },
    "metadata": {},
    "source": {}
  }
]